{
    "Ax": {
        "error": 1.7445800903978513e-07,
        "error_type": "SEM",
        "filter_outliers_dict": {
            "filter_outliers": false,
            "iterations": 1,
            "std_devs": 2
        },
        "fit": "average",
        "value": -7.621394653934977e-07
    },
    "H2": {
        "error": 1.238031799181717e-07,
        "error_type": "SEM",
        "filter_outliers_dict": {
            "filter_outliers": true,
            "iterations": 1,
            "std_devs": 2
        },
        "fit": "average",
        "value": -4.962847828335762e-07
    },
    "H4": {
        "error": 1.455908033238051e-07,
        "error_type": "SEM",
        "filter_outliers_dict": {
            "filter_outliers": true,
            "iterations": 1,
            "std_devs": 2
        },
        "fit": "average",
        "value": -4.781571347206896e-07
    },
    "L2": {
        "error": 1.2222032751577955e-07,
        "error_type": "SEM",
        "filter_outliers_dict": {
            "filter_outliers": true,
            "iterations": 1,
            "std_devs": 2
        },
        "fit": "average",
        "value": -5.135818990370142e-07
    },
    "L4": {
        "error": 5.33333333333333e-10,
        "error_type": "SEM",
        "filter_outliers_dict": {
            "filter_outliers": false,
            "iterations": 1,
            "std_devs": 2
        },
        "fit": "average",
        "value": 5.333333333333334e-10
    }
}